paypal/__init__.py
paypal/admin.py
paypal/base.py
paypal/exceptions.py
paypal/gateway.py
paypal/models.py
paypal/express/__init__.py
paypal/express/admin.py
paypal/express/exceptions.py
paypal/express/facade.py
paypal/express/gateway.py
paypal/express/models.py
paypal/express/urls.py
paypal/express/views.py
paypal/express/dashboard/__init__.py
paypal/express/dashboard/apps.py
paypal/express/dashboard/views.py
paypal/migrations/0001_initial.py
paypal/migrations/0002_auto_20190412_0732.py
paypal/migrations/__init__.py
paypal/payflow/__init__.py
paypal/payflow/admin.py
paypal/payflow/codes.py
paypal/payflow/facade.py
paypal/payflow/gateway.py
paypal/payflow/models.py
paypal/payflow/dashboard/__init__.py
paypal/payflow/dashboard/apps.py
paypal/payflow/dashboard/views.py
paypal/templates/paypal/express/preview.html
paypal/templates/paypal/express/dashboard/transaction_detail.html
paypal/templates/paypal/express/dashboard/transaction_list.html
paypal/templates/paypal/payflow/transaction_detail.html
paypal/templates/paypal/payflow/transaction_list.html
django_oscar_paypal-2.0.0.dist-info/AUTHORS
django_oscar_paypal-2.0.0.dist-info/LICENSE
django_oscar_paypal-2.0.0.dist-info/METADATA
django_oscar_paypal-2.0.0.dist-info/WHEEL
django_oscar_paypal-2.0.0.dist-info/top_level.txt
django_oscar_paypal-2.0.0.dist-info/RECORD
